insel/__init__.py
insel/existing_model.py
insel/insel.py
insel/insel_error.py
insel/model.py
insel/one_block_model.py
insel/template.py
insel/temporary_model.py
insel/tests/__init__.py
insel/tests/constants.py
insel/tests/custom_assertions.py
insel/tests/run_all_tests.py
insel/tests/test_blocks.py
insel/tests/test_doc.py
insel/tests/test_flags.py
insel/tests/test_models.py
insel/tests/test_templates.py
insel/tests/test_user_blocks.py
insel/tests/data/123.csv
insel/tests/data/123.dat
insel/tests/data/DEU_Stuttgart.107380_IWEC.epw
insel/tests/data/DEU_Stuttgart.107380_IWEC.txt
insel/tests/data/gengt_comparison.dat
insel/tests/templates/a_times_b.insel
insel/tests/templates/a_times_b_iso8859.insel
insel/tests/templates/a_times_b_utf8.insel
insel/tests/templates/add_negative_inputs.insel
insel/tests/templates/array_parameters.insel
insel/tests/templates/duplicate_constant.insel
insel/tests/templates/empty_constant.insel
insel/tests/templates/empty_if.insel
insel/tests/templates/expg.insel
insel/tests/templates/insel_constants.insel
insel/tests/templates/insel_include.insel
insel/tests/templates/merge_distinct_loops.insel
insel/tests/templates/odds_as_nans.insel
insel/tests/templates/one_to_ten.insel
insel/tests/templates/remove_odds.insel
insel/tests/templates/x1_plus_x2.insel
insel/tests/templates/conditional/average.insel
insel/tests/templates/conditional/max.insel
insel/tests/templates/conditional/min.insel
insel/tests/templates/conditional/sum.insel
insel/tests/templates/constants/both.insel
insel/tests/templates/constants/conflict.insel
insel/tests/templates/constants/nurnberg.vseit
insel/tests/templates/constants/same.insel
insel/tests/templates/constants/string_constant.insel
insel/tests/templates/constants/x_plus_y.vseit
insel/tests/templates/engine/do_do.insel
insel/tests/templates/engine/sum_sum.insel
insel/tests/templates/engine/sum_sum_do.insel
insel/tests/templates/io/long_string.vseit
insel/tests/templates/io/not_here.insel
insel-0.0.8.dist-info/LICENSE
insel-0.0.8.dist-info/METADATA
insel-0.0.8.dist-info/WHEEL
insel-0.0.8.dist-info/top_level.txt
insel-0.0.8.dist-info/RECORD
