Metadata-Version: 2.1
Name: insel
Version: 0.0.8
Summary: A python wrapper for INSEL (insel.eu)
Author-email: Eric Duminil <inselpy@ericduminil.com>
Project-URL: Homepage, https://github.com/EricDuminil/inselpy
Project-URL: Bug Tracker, https://github.com/EricDuminil/inselpy
Classifier: Programming Language :: Python :: 3
Classifier: License :: OSI Approved :: MIT License
Classifier: Operating System :: OS Independent
Requires-Python: >=3.7
License-File: LICENSE
